cmdcapture/__init__.py
cmdcapture/cli.py
cmdcapture/core.py
cmdcapture/exceptions.py
cmdcapture/utils.py
cmdcapture-1.0.0.dist-info/METADATA
cmdcapture-1.0.0.dist-info/WHEEL
cmdcapture-1.0.0.dist-info/entry_points.txt
cmdcapture-1.0.0.dist-info/top_level.txt
cmdcapture-1.0.0.dist-info/RECORD
