Metadata-Version: 2.4
Name: cmdcapture
Version: 1.0.0
Summary: A Python library for capturing output from terminal commands with advanced features
Home-page: https://github.com/Jejis06/CommandCapture
Author: Command Capture Library
Author-email: wertex3233@gmail.com
License: MIT
Project-URL: Homepage, https://github.com/Jejis06/CommandCapture
Project-URL: Bug Reports, https://github.com/Jejis06/CommandCapture/issues
Project-URL: Source, https://github.com/Jejis06/CommandCapture
Keywords: command,capture,subprocess,terminal,shell,output
Classifier: Programming Language :: Python :: 3
Classifier: Programming Language :: Python :: 3.7
Classifier: Programming Language :: Python :: 3.8
Classifier: Programming Language :: Python :: 3.9
Classifier: Programming Language :: Python :: 3.10
Classifier: Programming Language :: Python :: 3.11
Classifier: Programming Language :: Python :: 3.12
Classifier: License :: OSI Approved :: MIT License
Classifier: Operating System :: OS Independent
Classifier: Development Status :: 4 - Beta
Classifier: Intended Audience :: Developers
Classifier: Topic :: Software Development :: Libraries :: Python Modules
Classifier: Topic :: System :: Shells
Classifier: Topic :: Utilities
Requires-Python: >=3.7
Provides-Extra: dev
Requires-Dist: pytest>=6.0; extra == "dev"
Requires-Dist: pytest-cov>=2.0; extra == "dev"
Requires-Dist: black>=21.0; extra == "dev"
Requires-Dist: flake8>=3.8; extra == "dev"
Requires-Dist: mypy>=0.900; extra == "dev"
Dynamic: author-email
Dynamic: home-page
Dynamic: requires-python
